novabot_plugin_bupt_ncov/BUPT_User.py
novabot_plugin_bupt_ncov/__init__.py
novabot_plugin_bupt_ncov/exceptions.py
novabot_plugin_bupt_ncov/model.py
novabot_plugin_bupt_ncov/parser.py
novabot_plugin_bupt_ncov-0.1.1.dist-info/LICENSE
novabot_plugin_bupt_ncov-0.1.1.dist-info/WHEEL
novabot_plugin_bupt_ncov-0.1.1.dist-info/METADATA
novabot_plugin_bupt_ncov-0.1.1.dist-info/RECORD
