Metadata-Version: 2.1
Name: novabot-plugin-bupt-ncov
Version: 0.1.1
Summary: 
Author: NovaNo1r
Author-email: mail@novanoir.dev
Requires-Python: >=3.10,<4.0
Classifier: Programming Language :: Python :: 3
Classifier: Programming Language :: Python :: 3.10
Requires-Dist: aiohttp (>=3.8.1,<4.0.0)
Requires-Dist: nonebot2 (>=2.0.0-beta.5,<3.0.0)
Requires-Dist: pydantic (>=1.9.2,<2.0.0)
